{
    "fiscalYear": "FY3/2025",
    "companyName": "KOEI TECMO HOLDINGS CO., LTD.",
    "currentQuarter": 3,
    "data": [
        {
            "name": "Console Package & DL",
            "units": "currency",
            "Q1CmlValue": 6071,
            "Q2CmlValue": 11611,
            "Q3CmlValue": 18504,
            "Q4CmlValue": "Nothing",
            "footnotes": "Package: Including sales for packages, royalty, commission fees (incl. %-of-completion basis), and down payment. DL (download) sales: sales for digital copies via PSN/XboxLive/Switch DL/Steam" 
        },
        {
            "name": "Console Package & DL",
            "units": "units",
            "Q1CmlValue": 1370,
            "Q2CmlValue": 2660,
            "Q3CmlValue": 4340,
            "Q4CmlValue": "Nothing" 
        }
    ] 
    
}