{
    "currentQuarter": 4,
    "fiscalYear": " FY3/2019 ",
    "fiscalYearCml": " FY3/19 Cumulative ",
    "regions": [
        {
            "name": " Switch ",
            "regionA": "Global",
            "Q1CmlValueA": 188,
            "Q2CmlValueA": 507, 
            "Q3CmlValueA": 1449, 
            "Q4CmlValueA": 1695,
            "valueALastFY": 1779,
            "regionB": "Japan",
            "Q1CmlValueB": 50,
            "Q2CmlValueB": 114, 
            "Q3CmlValueB": 336, 
            "Q4CmlValueB": 385,
            "valueBLastFY": 438,
            "regionC": "The Americas",
            "Q1CmlValueC": 67,
            "Q2CmlValueC": 200, 
            "Q3CmlValueC": 580, 
            "Q4CmlValueC": 688,
            "valueCLastFY": 714,
            "regionD": "Europe",
            "Q1CmlValueD": 31,
            "Q2CmlValueD": 119, 
            "Q3CmlValueD": 396, 
            "Q4CmlValueD": 455,
            "valueDLastFY": 454,
            "regionE": "Other",
            "Q1CmlValueE": 40,
            "Q2CmlValueE": 74, 
            "Q3CmlValueE": 137, 
            "Q4CmlValueE": 169,
            "valueELastFY": 172,
            "dataShift": true 
        },
        {
            "name": " Nintendo Switch Hardware Total ",
            "regionA": "Global",
            "Q1CmlValueA": 188,
            "Q2CmlValueA": 507, 
            "Q3CmlValueA": 1449, 
            "Q4CmlValueA": 1695,
            "valueALastFY": 1779,
            "regionB": "Japan",
            "Q1CmlValueB": 50,
            "Q2CmlValueB": 114, 
            "Q3CmlValueB": 336, 
            "Q4CmlValueB": 385,
            "valueBLastFY": 438,
            "regionC": "The Americas",
            "Q1CmlValueC": 67,
            "Q2CmlValueC": 200, 
            "Q3CmlValueC": 580, 
            "Q4CmlValueC": 688,
            "valueCLastFY": 714,
            "regionD": "Europe",
            "Q1CmlValueD": 31,
            "Q2CmlValueD": 119, 
            "Q3CmlValueD": 396, 
            "Q4CmlValueD": 455,
            "valueDLastFY": 454,
            "regionE": "Other",
            "Q1CmlValueE": 40,
            "Q2CmlValueE": 74, 
            "Q3CmlValueE": 137, 
            "Q4CmlValueE": 169,
            "valueELastFY": 172 
        },
        {
            "name": " Nintendo Switch Software Total ",
            "regionA": "Global",
            "Q1CmlValueA": 1796,
            "Q2CmlValueA": 4213,
            "Q3CmlValueA": 9464,
            "Q4CmlValueA": 11855,
            "valueALastFY": 6897,
            "regionB": "Japan",
            "Q1CmlValueB": 295,
            "Q2CmlValueB": 715,
            "Q3CmlValueB": 1718,
            "Q4CmlValueB": 2148,
            "valueBLastFY": 1315,
            "regionC": "The Americas",
            "Q1CmlValueC": 837,
            "Q2CmlValueC": 1960,
            "Q3CmlValueC": 4348,
            "Q4CmlValueC": 5394,
            "valueCLastFY": 3038,
            "regionD": "Europe",
            "Q1CmlValueD": 524,
            "Q2CmlValueD": 1284,
            "Q3CmlValueD": 2786,
            "Q4CmlValueD": 3516,
            "valueDLastFY": 2059,
            "regionE": "Other",
            "Q1CmlValueE": 141,
            "Q2CmlValueE": 253,
            "Q3CmlValueE": 612,
            "Q4CmlValueE": 797,
            "valueELastFY": 486 
        },
        {"name":"Nintendo 3DS Hardware","regionA":"Global","Q1CmlValueA":20,"Q2CmlValueA":37,"Q3CmlValueA":62,"Q4CmlValueA":69,"valueALastFY":7508,"regionB":"Japan","Q1CmlValueB":3,"Q2CmlValueB":4,"Q3CmlValueB":6,"Q4CmlValueB":9,"valueBLastFY":2517,"regionC":"The Americas","Q1CmlValueC":9,"Q2CmlValueC":18,"Q3CmlValueC":28,"Q4CmlValueC":28,"valueCLastFY":2645,"regionD":"Other","Q1CmlValueD":8,"Q2CmlValueD":15,"Q3CmlValueD":29,"Q4CmlValueD":32,"valueDLastFY":2346,"regionE":"Other","Q1CmlValueE":0,"Q2CmlValueE":0,"Q3CmlValueE":0,"Q4CmlValueE":0,"valueELastFY":0},{"name":"Nintendo 3DS Software","regionA":"Global","Q1CmlValueA":148,"Q2CmlValueA":260,"Q3CmlValueA":410,"Q4CmlValueA":499,"valueALastFY":37812,"regionB":"Japan","Q1CmlValueB":17,"Q2CmlValueB":28,"Q3CmlValueB":36,"Q4CmlValueB":48,"valueBLastFY":13695,"regionC":"The Americas","Q1CmlValueC":68,"Q2CmlValueC":122,"Q3CmlValueC":196,"Q4CmlValueC":234,"valueCLastFY":12851,"regionD":"Other","Q1CmlValueD":63,"Q2CmlValueD":110,"Q3CmlValueD":178,"Q4CmlValueD":217,"valueDLastFY":11266,"regionE":"Other","Q1CmlValueE":0,"Q2CmlValueE":0,"Q3CmlValueE":0,"Q4CmlValueE":0,"valueELastFY":0}
    ]
}