{
    "currentQuarter": 4,
    "companyName": "Nintendo Co., Ltd.",
    "fiscalYear": "FY3/1996",
    "data": [
        {
            "name": "Net Sales",
            "units":"currency",
            "Q1CmlValue": "Nothing",
            "Q2CmlValue": "Nothing",
            "Q3CmlValue": "Nothing",
            "Q4CmlValue": 354152
        },
        {
            "name": "Operating Income",
            "units":"currency",
            "Q1CmlValue": "Nothing",
            "Q2CmlValue": "Nothing",
            "Q3CmlValue": "Nothing",
            "Q4CmlValue": 71939
        },
        {
            "name": "Net Income",
            "units":"currency",
            "Q1CmlValue": "Nothing",
            "Q2CmlValue": "Nothing",
            "Q3CmlValue": "Nothing",
            "Q4CmlValue": 59870
        }
    ]
}