{
    "currentQuarter": 4,
    "companyName": "KADOKAWA CORPORATION",
    "fiscalYear": "FY3/2015",
    "data": [
        {
            "name": "Publication",
            "units": "currency",
            "ID": "1",
            "Q1CmlValue": {
                "netSales": 27440,
                "operatingIncome": 1268
            },
            "Q2CmlValue": {
                "netSales": "Nothing",
                "operatingIncome":"Nothing" 
            },
            "Q3CmlValue": {
                "netSales": "Nothing",
                "operatingIncome":"Nothing" 
            },
            "Q4CmlValue": {
                "netSales": 54296,
                "operatingIncome": 1874
            },
            "forecastThisFY": {
                "netSales": "Nothing",
                "operatingIncome": "Nothing"
            },
            "forecastRevision1": {
                "netSales": null,
                "operatingIncome": null
            },
            "forecastRevision2": {
                "netSales": null,
                "operatingIncome": null
            },
            "forecastRevision3": {
                "netSales": null,
                "operatingIncome": null
            },
            "forecastNextFY": {
                "netSales": "Nothing",
                "operatingIncome": "Nothing"
            }
        },
        {
            "name": "Video and Game",
            "units": "currency",
            "ID": "2",
            "Q1CmlValue": {
                "netSales": 12260,
                "operatingIncome": 1057
            },
            "Q2CmlValue": {
                "netSales": "Nothing",
                "operatingIncome":"Nothing" 
            },
            "Q3CmlValue": {
                "netSales": "Nothing",
                "operatingIncome":"Nothing" 
            },
            "Q4CmlValue": {
                "netSales": 23035,
                "operatingIncome": -28
            },
            "forecastThisFY": {
                "netSales": "Nothing",
                "operatingIncome": "Nothing"
            },
            "forecastRevision1": {
                "netSales": null,
                "operatingIncome": null
            },
            "forecastRevision2": {
                "netSales": null,
                "operatingIncome": null
            },
            "forecastRevision3": {
                "netSales": null,
                "operatingIncome": null
            },
            "forecastNextFY": {
                "netSales": "Nothing",
                "operatingIncome": "Nothing"
            }
        },
        {
            "name": "Web services",
            "units": "currency",
            "ID": "4",
            "Q1CmlValue": {
                "netSales": 7842,
                "operatingIncome": 1449
            },
            "Q2CmlValue": {
                "netSales": "Nothing",
                "operatingIncome":"Nothing" 
            },
            "Q3CmlValue": {
                "netSales": "Nothing",
                "operatingIncome":"Nothing" 
            },
            "Q4CmlValue": {
                "netSales": 15722,
                "operatingIncome": 2674
            },
            "forecastThisFY": {
                "netSales": "Nothing",
                "operatingIncome": "Nothing"
            },
            "forecastRevision1": {
                "netSales": null,
                "operatingIncome": null
            },
            "forecastRevision2": {
                "netSales": null,
                "operatingIncome": null
            },
            "forecastRevision3": {
                "netSales": null,
                "operatingIncome": null
            },
            "forecastNextFY": {
                "netSales": "Nothing",
                "operatingIncome": "Nothing"
            }
        },
        {
            "name": "Others",
            "units": "currency",
            "ID": "5",
            "Q1CmlValue": {
                "netSales": 3447,
                "operatingIncome": -163
            },
            "Q2CmlValue": {
                "netSales": "Nothing",
                "operatingIncome":"Nothing" 
            },
            "Q3CmlValue": {
                "netSales": "Nothing",
                "operatingIncome":"Nothing" 
            },
            "Q4CmlValue": {
                "netSales": 9620,
                "operatingIncome": -326
            },
            "forecastThisFY": {
                "netSales": "Nothing",
                "operatingIncome": "Nothing"
            },
            "forecastRevision1": {
                "netSales": null,
                "operatingIncome": null
            },
            "forecastRevision2": {
                "netSales": null,
                "operatingIncome": null
            },
            "forecastRevision3": {
                "netSales": null,
                "operatingIncome": null
            },
            "forecastNextFY": {
                "netSales": "Nothing",
                "operatingIncome": "Nothing"
            }
        }
    ] 
}