{
    "fiscalYear": "FY3/2007",
    "data": [
        {
            "text": "1st Quarter Earnings Release:",
            "link": "https://www.hd.square-enix.com/eng/pdf/financial_20060804_01.pdf"
        },
        {
            "text": "2nd Quarter Earnings Release:",
            "link": "https://www.hd.square-enix.com/eng/pdf/financial_20061117_01.pdf"
        },
        {
            "text": "3rd Quarter Earnings Release:",
            "link": "https://www.hd.square-enix.com/eng/pdf/financial_20070130_01.pdf"
        },
        {
            "text": "4th Quarter Earnings Release:",
            "link": "https://www.hd.square-enix.com/eng/pdf/financial_20070523_01.pdf"
        }
    ]
}