{
    "fiscalYear": "FY3/2020",
    "data": [
        {
            "text": "1st Quarter Earnings Release:",
            "link": "https://www.hd.square-enix.com/eng/news/pdf/20q1earnings.pdf"
        },
        {
            "text": "1st Quarter Financial Results Presentation:",
            "link": "https://www.hd.square-enix.com/eng/ir/library/pdf/20q1slides.pdf"
        },
        {
            "text": "2nd Quarter Earnings Release:",
            "link": "https://www.hd.square-enix.com/eng/news/pdf/20q2earnings.pdf"
        },
        {
            "text": "2nd Quarter Financial Results Presentation:",
            "link": "https://www.hd.square-enix.com/eng/ir/library/pdf/20q2slides.pdf"
        },
        {
            "text": "3rd Quarter Earnings Release:",
            "link": "https://www.hd.square-enix.com/eng/news/pdf/20q3earnings.pdf"
        },
        {
            "text": "3rd Quarter Financial Results Presentation:",
            "link": "https://www.hd.square-enix.com/eng/ir/library/pdf/20q3slides.pdf"
        },
        {
            "text": "4th Quarter Earnings Release:",
            "link": "https://www.hd.square-enix.com/eng/news/pdf/20q4earnings.pdf"
        },
        {
            "text": "4th Quarter Financial Results Presentation:",
            "link": "https://www.hd.square-enix.com/eng/ir/library/pdf/20q4slides.pdf"
        },
        {
            "text": "Annual Report 2020:",
            "link": "https://www.hd.square-enix.com/eng/ir/library/pdf/ar_2020en.pdf"
        },
        {
            "text": "Press Release for Q4 Fiscal Year Ending March 2020:",
            "link": "https://www.hd.square-enix.com/eng/ir/pdf/20q4release.pdf"
        }
    ]
}